cvcuda/__init__.py
cvcuda/_load_binding.py
cvcuda/_bindings/cvcuda.cpython-312-x86_64-linux-gnu.so
cvcuda/_bindings/cvcuda.cpython-310-x86_64-linux-gnu.so
cvcuda/_bindings/cvcuda.cpython-311-x86_64-linux-gnu.so
cvcuda/_bindings/cvcuda.cpython-313-x86_64-linux-gnu.so
cvcuda/_bindings/cvcuda.cpython-39-x86_64-linux-gnu.so
cvcuda/_bindings/cvcuda.cpython-38-x86_64-linux-gnu.so
nvcv/__init__.py
nvcv/_load_binding.py
nvcv/_bindings/nvcv.cpython-39-x86_64-linux-gnu.so
nvcv/_bindings/nvcv.cpython-312-x86_64-linux-gnu.so
nvcv/_bindings/nvcv.cpython-310-x86_64-linux-gnu.so
nvcv/_bindings/nvcv.cpython-311-x86_64-linux-gnu.so
nvcv/_bindings/nvcv.cpython-313-x86_64-linux-gnu.so
nvcv/_bindings/nvcv.cpython-38-x86_64-linux-gnu.so
cvcuda_cu11-0.15.0.dist-info/WHEEL
cvcuda_cu11-0.15.0.dist-info/top_level.txt
cvcuda_cu11-0.15.0.dist-info/RECORD
cvcuda_cu11-0.15.0.dist-info/METADATA
cvcuda_cu11.libs/libnvcv_types-389880fd.so.0.15.0
cvcuda_cu11.libs/libcvcuda-ee020595.so.0.15.0
